redzed/__init__.py
redzed/base_block.py
redzed/block.py
redzed/circuit.py
redzed/cron_service.py
redzed/debug.py
redzed/formula_trigger.py
redzed/initializers.py
redzed/signal_shutdown.py
redzed/undef.py
redzed/blocklib/__init__.py
redzed/blocklib/counter.py
redzed/blocklib/fsm.py
redzed/blocklib/inputs.py
redzed/blocklib/outputs.py
redzed/blocklib/repeat.py
redzed/blocklib/timedate.py
redzed/blocklib/timeinterval.py
redzed/blocklib/timer.py
redzed/utils/__init__.py
redzed/utils/async_utils.py
redzed/utils/data_utils.py
redzed/utils/time_utils.py
redzed-25.12.30.dist-info/licenses/LICENSE.txt
redzed-25.12.30.dist-info/METADATA
redzed-25.12.30.dist-info/WHEEL
redzed-25.12.30.dist-info/top_level.txt
redzed-25.12.30.dist-info/RECORD
