Metadata-Version: 2.4
Name: redzed
Version: 25.12.30
Summary: An asyncio-based library for building small automated systems
Author-email: Vlado Potisk <redzed@poti.sk>
License-Expression: MIT
Project-URL: homepage, https://github.com/xitop/redzed
Project-URL: repository, https://github.com/xitop/redzed
Project-URL: documentation, https://redzed.readthedocs.io/en/latest/
Keywords: automation,finite-state machine
Classifier: Development Status :: 3 - Alpha
Classifier: Intended Audience :: Developers
Classifier: Topic :: Software Development :: Libraries :: Python Modules
Classifier: Programming Language :: Python :: 3
Requires-Python: >=3.11
License-File: LICENSE.txt
Provides-Extra: tests
Requires-Dist: pytest>=8.4.0; extra == "tests"
Requires-Dist: pytest-asyncio>=0.26.0; extra == "tests"
Requires-Dist: pytest-xdist; extra == "tests"
Dynamic: license-file
